pipen_log2file.py
pipen_log2file-1.0.1.dist-info/METADATA
pipen_log2file-1.0.1.dist-info/WHEEL
pipen_log2file-1.0.1.dist-info/entry_points.txt
pipen_log2file-1.0.1.dist-info/licenses/LICENSE
pipen_log2file-1.0.1.dist-info/RECORD
