Metadata-Version: 2.4
Name: pipen-log2file
Version: 1.0.1
Summary: Add verbosal information in logs for pipen.
License: MIT
License-File: LICENSE
Author: pwwang
Author-email: pwwang@pwwang.com
Requires-Python: >=3.9,<4.0
Classifier: License :: OSI Approved :: MIT License
Classifier: Programming Language :: Python :: 3
Classifier: Programming Language :: Python :: 3.9
Classifier: Programming Language :: Python :: 3.10
Classifier: Programming Language :: Python :: 3.11
Classifier: Programming Language :: Python :: 3.12
Classifier: Programming Language :: Python :: 3.13
Classifier: Programming Language :: Python :: 3.14
Requires-Dist: pipen (>=1.0,<2.0)
Project-URL: Homepage, https://github.com/pwwang/pipen-log2file
Project-URL: Repository, https://github.com/pwwang/pipen-log2file
